py4eos/__init__.py
py4eos/srs.py
py4eos-0.6.0.dist-info/licenses/LICENSE
py4eos-0.6.0.dist-info/METADATA
py4eos-0.6.0.dist-info/WHEEL
py4eos-0.6.0.dist-info/top_level.txt
py4eos-0.6.0.dist-info/RECORD
