Metadata-Version: 2.4
Name: py4eos
Version: 0.6.0
Summary: Convenience functions for working with HDF4-EOS datasets
Author-email: "K. Arthur Endsley" <arthur.endsley@ntsg.umt.edu>
License-Expression: MIT
Classifier: Programming Language :: Python :: 3
Classifier: Development Status :: 3 - Alpha
Classifier: Intended Audience :: Science/Research
Classifier: Topic :: Scientific/Engineering
Requires-Python: >=3.8
License-File: LICENSE
Requires-Dist: numpy<2.0.0
Requires-Dist: rasterio>=1.0.0
Requires-Dist: affine>=2.0.0
Requires-Dist: pyhdf>=0.11.0
Requires-Dist: h5py>=3.0.0
Provides-Extra: dev
Requires-Dist: pytest>=8.0.0; extra == "dev"
Requires-Dist: earthaccess>=0.9.0; extra == "dev"
Requires-Dist: pdoc3>=0.9.2; extra == "dev"
Dynamic: license-file
